tg_notification_bot/__init__.py
tg_notification_bot/bot.py
tg_notification_bot/exceptions.py
tg_notification_bot/models.py
tg_notification_bot-1.0.0.dist-info/METADATA
tg_notification_bot-1.0.0.dist-info/WHEEL
tg_notification_bot-1.0.0.dist-info/top_level.txt
tg_notification_bot-1.0.0.dist-info/RECORD
