Metadata-Version: 2.4
Name: tg-notification-bot
Version: 1.0.0
Summary: Modern Telegram notification bot library for Python projects with multi-chat support
Author-email: AI-Stratov <workistratov@gmail.com>
License-Expression: MIT
Project-URL: Homepage, https://github.com/AI-Stratov/tg-notification-bot
Project-URL: Repository, https://github.com/AI-Stratov/tg-notification-bot
Project-URL: Issues, https://github.com/AI-Stratov/tg-notification-bot/issues
Project-URL: Documentation, https://github.com/AI-Stratov/tg-notification-bot#readme
Keywords: telegram,bot,notifications,aiogram,multi-chat,bulk-sending
Classifier: Development Status :: 5 - Production/Stable
Classifier: Intended Audience :: Developers
Classifier: Programming Language :: Python :: 3
Classifier: Programming Language :: Python :: 3.9
Classifier: Programming Language :: Python :: 3.10
Classifier: Programming Language :: Python :: 3.11
Classifier: Programming Language :: Python :: 3.12
Classifier: Programming Language :: Python :: 3.13
Classifier: Topic :: Communications :: Chat
Classifier: Topic :: Software Development :: Libraries :: Python Modules
Requires-Python: >=3.9
Requires-Dist: aiogram<4.0.0,>=3.15.0
Requires-Dist: pydantic<3.0.0,>=2.0.0
Provides-Extra: dev
Requires-Dist: pytest>=7.0.0; extra == "dev"
Requires-Dist: pytest-asyncio>=0.21.0; extra == "dev"
Requires-Dist: pytest-mock>=3.10.0; extra == "dev"
Requires-Dist: ruff>=0.1.0; extra == "dev"
Requires-Dist: mypy>=1.0.0; extra == "dev"
